mdbookhtml2pdf/__init__.py
mdbookhtml2pdf/code_highlighter.py
mdbookhtml2pdf/cover_generator.py
mdbookhtml2pdf/mdbookhtml2pdf.py
mdbookhtml2pdf/mermaid_processor.py
mdbookhtml2pdf/processor.py
mdbookhtml2pdf/toc_generator.py
mdbookhtml2pdf/utils.py
mdbookhtml2pdf-0.2.0.dist-info/METADATA
mdbookhtml2pdf-0.2.0.dist-info/WHEEL
mdbookhtml2pdf-0.2.0.dist-info/entry_points.txt
mdbookhtml2pdf-0.2.0.dist-info/top_level.txt
mdbookhtml2pdf-0.2.0.dist-info/RECORD
