Metadata-Version: 2.1
Name: mdbookhtml2pdf
Version: 0.2.0
Summary: Convert mdBook HTML to PDF with TOC, code highlighting and mermaid diagrams
Home-page: https://gitee.com/jakHall/mdbookhtml2pdf.git
Author: min
Author-email: testmin@outlook.com
License: UNKNOWN
Platform: UNKNOWN
Classifier: Programming Language :: Python :: 3
Classifier: License :: OSI Approved :: MIT License
Classifier: Operating System :: OS Independent
Requires-Python: >=3.7
Requires-Dist: Pygments (>=2.10.0)
Requires-Dist: beautifulsoup4 (>=4.9.3)
Requires-Dist: weasyprint (>=52.5)
